eynnyd/__init__.py
eynnyd/abstract_request.py
eynnyd/abstract_response.py
eynnyd/error_handlers_builder.py
eynnyd/exceptions.py
eynnyd/eynnyd_webapp_builder.py
eynnyd/response_builder.py
eynnyd/response_cookie_builder.py
eynnyd/routes_builder.py
eynnyd/internal/__init__.py
eynnyd/internal/eynnyd_webapp.py
eynnyd/internal/response.py
eynnyd/internal/response_body.py
eynnyd/internal/response_body_type.py
eynnyd/internal/wsgi_loaded_request.py
eynnyd/internal/plan_execution/__init__.py
eynnyd/internal/plan_execution/default_error_handlers.py
eynnyd/internal/plan_execution/error_handlers.py
eynnyd/internal/plan_execution/execution_plan.py
eynnyd/internal/plan_execution/execution_plan_builder.py
eynnyd/internal/plan_execution/plan_executor.py
eynnyd/internal/routing/__init__.py
eynnyd/internal/routing/pattern_route.py
eynnyd/internal/routing/pattern_route_builder.py
eynnyd/internal/routing/route_tree_builder.py
eynnyd/internal/routing/route_tree_node.py
eynnyd/internal/routing/route_tree_traverser.py
eynnyd/internal/utils/__init__.py
eynnyd/internal/utils/header_helpers.py
eynnyd/internal/utils/http_status.py
eynnyd/internal/utils/http_status_factory.py
eynnyd/internal/utils/http_status_groups.py
eynnyd/internal/utils/request_uri.py
eynnyd/internal/utils/uri_components_converter.py
eynnyd/internal/utils/cookies/__init__.py
eynnyd/internal/utils/cookies/header_converter.py
eynnyd/internal/utils/cookies/request_cookie.py
eynnyd/internal/utils/cookies/response_cookie.py
eynnyd/internal/utils/cookies/rfc.py
eynnyd/internal/wsgi/__init__.py
eynnyd/internal/wsgi/abstract_response_body.py
eynnyd/internal/wsgi/byte_response_body.py
eynnyd/internal/wsgi/closeable_stream_iterator.py
eynnyd/internal/wsgi/empty_response_body.py
eynnyd/internal/wsgi/iterable_response_body.py
eynnyd/internal/wsgi/raw_wsgi_server_error_response.py
eynnyd/internal/wsgi/stream_reader_factory.py
eynnyd/internal/wsgi/stream_response_body.py
eynnyd/internal/wsgi/utf8_response_body.py
eynnyd-0.4.1.dist-info/LICENSE
eynnyd-0.4.1.dist-info/METADATA
eynnyd-0.4.1.dist-info/WHEEL
eynnyd-0.4.1.dist-info/top_level.txt
eynnyd-0.4.1.dist-info/RECORD
