Metadata-Version: 2.1
Name: eynnyd
Version: 0.4.1
Summary: A light-weight wsgi web framework
Home-page: https://eynnyd.readthedocs.io/en/latest/
Author: Chad Befus
Author-email: crbefus@gmail.com
License: MIT License
Keywords: wsgi web framework api rest http
Platform: UNKNOWN
Classifier: Development Status :: 5 - Production/Stable
Classifier: Intended Audience :: Developers
Classifier: License :: OSI Approved :: MIT License
Classifier: Natural Language :: English
Classifier: Operating System :: OS Independent
Classifier: Programming Language :: Python
Classifier: Programming Language :: Python :: 3
Classifier: Programming Language :: Python :: 3.5
Classifier: Programming Language :: Python :: 3.6
Classifier: Programming Language :: Python :: 3.7
Classifier: Operating System :: MacOS :: MacOS X
Classifier: Operating System :: Microsoft :: Windows
Classifier: Operating System :: POSIX
Classifier: Topic :: Internet :: WWW/HTTP :: WSGI
Classifier: Topic :: Software Development :: Libraries :: Application Frameworks
Requires-Python: >=3.5
Requires-Dist: arrow (<=1.0.0,>=0.14.4)
Requires-Dist: optional.py (<=2.0.0,>=1.0.0)
